text2image_api/__init__.py
text2image_api/module.py
text2video/__init__.py
text2video/module.py
text2image_api-0.0.1.dist-info/METADATA
text2image_api-0.0.1.dist-info/WHEEL
text2image_api-0.0.1.dist-info/top_level.txt
text2image_api-0.0.1.dist-info/RECORD
